{"file": "rotated_Screenshot (189)_105.jpg", "image_size": [{"width": 1656, "height": 2165, "depth": 3}], "annotations": [{"class_id": 1, "top": 1101, "left": 417, "width": 160, "height": 165}, {"class_id": 1, "top": 1209, "left": 1130, "width": 126, "height": 138}, {"class_id": 1, "top": 781, "left": 624, "width": 159, "height": 162}, {"class_id": 1, "top": 665, "left": 599, "width": 130, "height": 143}, {"class_id": 0, "top": 1093, "left": 520, "width": 133, "height": 144}, {"class_id": 1, "top": 1352, "left": 899, "width": 95, "height": 115}, {"class_id": 0, "top": 744, "left": 1069, "width": 44, "height": 45}, {"class_id": 0, "top": 693, "left": 1091, "width": 45, "height": 47}, {"class_id": 0, "top": 678, "left": 1016, "width": 46, "height": 48}, {"class_id": 0, "top": 673, "left": 975, "width": 46, "height": 42}, {"class_id": 1, "top": 727, "left": 1121, "width": 43, "height": 43}, {"class_id": 0, "top": 751, "left": 1021, "width": 55, "height": 58}, {"class_id": 0, "top": 687, "left": 939, "width": 44, "height": 40}, {"class_id": 0, "top": 579, "left": 1059, "width": 54, "height": 44}, {"class_id": 0, "top": 627, "left": 1127, "width": 47, "height": 46}, {"class_id": 1, "top": 569, "left": 1125, "width": 41, "height": 41}], "categories": [{"class_id": 0, "name": "3clover"}, {"class_id": 1, "name": "4clover"}]}