{"file": "rotated_Screenshot (257)_315.jpg", "image_size": [{"width": 2206, "height": 2206, "depth": 3}], "annotations": [{"class_id": 1, "top": 588, "left": 1010, "width": 145, "height": 145}, {"class_id": 1, "top": 818, "left": 1239, "width": 141, "height": 141}, {"class_id": 1, "top": 1031, "left": 1453, "width": 165, "height": 165}, {"class_id": 1, "top": 1227, "left": 751, "width": 214, "height": 214}, {"class_id": 0, "top": 1177, "left": 1457, "width": 143, "height": 143}, {"class_id": 0, "top": 1026, "left": 1360, "width": 172, "height": 172}], "categories": [{"class_id": 0, "name": "3clover"}, {"class_id": 1, "name": "4clover"}]}