{"file": "rotated_Screenshot (243)_45.jpg", "image_size": [{"width": 2206, "height": 2206, "depth": 3}], "annotations": [{"class_id": 1, "top": 1270, "left": 798, "width": 177, "height": 177}, {"class_id": 1, "top": 1033, "left": 1033, "width": 171, "height": 171}, {"class_id": 1, "top": 1303, "left": 1293, "width": 158, "height": 158}, {"class_id": 1, "top": 1021, "left": 1450, "width": 209, "height": 209}, {"class_id": 0, "top": 561, "left": 1116, "width": 142, "height": 142}, {"class_id": 1, "top": 794, "left": 1227, "width": 165, "height": 165}, {"class_id": 0, "top": 1426, "left": 847, "width": 82, "height": 82}, {"class_id": 0, "top": 1125, "left": 1184, "width": 91, "height": 91}, {"class_id": 0, "top": 1099, "left": 1146, "width": 86, "height": 86}, {"class_id": 0, "top": 1024, "left": 1158, "width": 93, "height": 93}, {"class_id": 1, "top": 579, "left": 1029, "width": 168, "height": 168}, {"class_id": 1, "top": 1003, "left": 587, "width": 106, "height": 106}, {"class_id": 0, "top": 1109, "left": 623, "width": 101, "height": 101}], "categories": [{"class_id": 0, "name": "3clover"}, {"class_id": 1, "name": "4clover"}]}