{"file": "rotated_Screenshot (141)_60.jpg", "image_size": [{"width": 1999, "height": 2262, "depth": 3}], "annotations": [{"class_id": 1, "top": 1239, "left": 465, "width": 160, "height": 171}, {"class_id": 1, "top": 1315, "left": 1246, "width": 92, "height": 94}, {"class_id": 1, "top": 974, "left": 1393, "width": 197, "height": 191}, {"class_id": 1, "top": 949, "left": 683, "width": 112, "height": 114}, {"class_id": 1, "top": 510, "left": 693, "width": 400, "height": 399}], "categories": [{"class_id": 1, "name": "4clover"}]}