{"file": "rotated_32ecd94d7f5c4c158310f8d2330d76dd_255.jpg", "image_size": [{"width": 1656, "height": 2165, "depth": 3}], "annotations": [{"class_id": 1, "top": 626, "left": 766, "width": 244, "height": 257}, {"class_id": 1, "top": 589, "left": 527, "width": 186, "height": 191}, {"class_id": 1, "top": 1245, "left": 438, "width": 101, "height": 94}, {"class_id": 0, "top": 561, "left": 693, "width": 73, "height": 73}], "categories": [{"class_id": 0, "name": "3clover"}, {"class_id": 1, "name": "4clover"}]}