{"file": "rotated_Screenshot (173)_15.jpg", "image_size": [{"width": 2165, "height": 1656, "depth": 3}], "annotations": [{"class_id": 1, "top": 712, "left": 1325, "width": 203, "height": 208}, {"class_id": 1, "top": 861, "left": 685, "width": 107, "height": 117}, {"class_id": 0, "top": 613, "left": 566, "width": 101, "height": 94}, {"class_id": 0, "top": 541, "left": 605, "width": 103, "height": 92}, {"class_id": 0, "top": 725, "left": 606, "width": 84, "height": 79}, {"class_id": 0, "top": 698, "left": 551, "width": 82, "height": 96}, {"class_id": 0, "top": 949, "left": 734, "width": 83, "height": 86}, {"class_id": 0, "top": 967, "left": 830, "width": 123, "height": 133}, {"class_id": 0, "top": 995, "left": 652, "width": 121, "height": 116}, {"class_id": 1, "top": 491, "left": 1282, "width": 87, "height": 85}, {"class_id": 1, "top": 621, "left": 658, "width": 91, "height": 102}, {"class_id": 0, "top": 729, "left": 713, "width": 70, "height": 75}, {"class_id": 0, "top": 855, "left": 811, "width": 86, "height": 80}, {"class_id": 0, "top": 534, "left": 732, "width": 87, "height": 99}], "categories": [{"class_id": 0, "name": "3clover"}, {"class_id": 1, "name": "4clover"}]}