{"file": "rotated_Screenshot (83)_210.jpg", "image_size": [{"width": 2262, "height": 1999, "depth": 3}], "annotations": [{"class_id": 1, "top": 985, "left": 1487, "width": 128, "height": 122}, {"class_id": 1, "top": 892, "left": 1127, "width": 137, "height": 137}, {"class_id": 1, "top": 875, "left": 1021, "width": 146, "height": 149}, {"class_id": 1, "top": 846, "left": 964, "width": 108, "height": 109}, {"class_id": 1, "top": 720, "left": 572, "width": 154, "height": 151}, {"class_id": 1, "top": 462, "left": 1087, "width": 175, "height": 161}, {"class_id": 0, "top": 414, "left": 1221, "width": 160, "height": 157}], "categories": [{"class_id": 0, "name": "3clover"}, {"class_id": 1, "name": "4clover"}]}