{"file": "rotated_Screenshot (31)_90.jpg", "image_size": [{"width": 1200, "height": 1920, "depth": 3}], "annotations": [{"class_id": 1, "top": 1244, "left": 602, "width": 104, "height": 93}, {"class_id": 1, "top": 1269, "left": 950, "width": 90, "height": 87}, {"class_id": 1, "top": 902, "left": 922, "width": 137, "height": 140}, {"class_id": 1, "top": 894, "left": 566, "width": 195, "height": 181}, {"class_id": 1, "top": 578, "left": 926, "width": 122, "height": 116}, {"class_id": 1, "top": 997, "left": 359, "width": 75, "height": 124}, {"class_id": 1, "top": 851, "left": 362, "width": 92, "height": 120}], "categories": [{"class_id": 1, "name": "4clover"}]}