{"file": "rotated_Screenshot (6)_15.jpg", "image_size": [{"width": 2165, "height": 1656, "depth": 3}], "annotations": [{"class_id": 1, "top": 403, "left": 863, "width": 304, "height": 297}, {"class_id": 1, "top": 575, "left": 643, "width": 110, "height": 109}, {"class_id": 1, "top": 834, "left": 1040, "width": 81, "height": 76}, {"class_id": 0, "top": 765, "left": 1052, "width": 67, "height": 64}, {"class_id": 0, "top": 836, "left": 939, "width": 49, "height": 50}, {"class_id": 0, "top": 777, "left": 964, "width": 68, "height": 63}, {"class_id": 0, "top": 924, "left": 1088, "width": 98, "height": 88}, {"class_id": 0, "top": 734, "left": 946, "width": 68, "height": 55}, {"class_id": 0, "top": 637, "left": 613, "width": 113, "height": 100}, {"class_id": 0, "top": 499, "left": 666, "width": 68, "height": 67}, {"class_id": 0, "top": 476, "left": 705, "width": 60, "height": 72}, {"class_id": 0, "top": 494, "left": 602, "width": 78, "height": 76}, {"class_id": 0, "top": 608, "left": 559, "width": 86, "height": 96}], "categories": [{"class_id": 0, "name": "3clover"}, {"class_id": 1, "name": "4clover"}]}