{"file": "rotated_481911447e124721aa471b39219a4df1_330.jpg", "image_size": [{"width": 2262, "height": 1999, "depth": 3}], "annotations": [{"class_id": 1, "top": 710, "left": 1190, "width": 111, "height": 109}, {"class_id": 1, "top": 1030, "left": 514, "width": 234, "height": 239}, {"class_id": 1, "top": 989, "left": 1034, "width": 116, "height": 119}, {"class_id": 1, "top": 1166, "left": 1340, "width": 156, "height": 158}, {"class_id": 1, "top": 849, "left": 1526, "width": 111, "height": 107}, {"class_id": 0, "top": 984, "left": 982, "width": 98, "height": 98}, {"class_id": 0, "top": 1103, "left": 1051, "width": 82, "height": 86}, {"class_id": 0, "top": 1131, "left": 1451, "width": 105, "height": 108}, {"class_id": 0, "top": 909, "left": 1014, "width": 107, "height": 103}, {"class_id": 0, "top": 949, "left": 1349, "width": 87, "height": 81}, {"class_id": 0, "top": 995, "left": 1422, "width": 65, "height": 65}, {"class_id": 0, "top": 837, "left": 1619, "width": 75, "height": 76}, {"class_id": 0, "top": 1165, "left": 542, "width": 222, "height": 213}], "categories": [{"class_id": 0, "name": "3clover"}, {"class_id": 1, "name": "4clover"}]}