{"file": "rotated_Screenshot (111)_135.jpg", "image_size": [{"width": 2206, "height": 2206, "depth": 3}], "annotations": [{"class_id": 1, "top": 1127, "left": 1410, "width": 133, "height": 133}, {"class_id": 1, "top": 875, "left": 1254, "width": 51, "height": 51}, {"class_id": 0, "top": 805, "left": 800, "width": 127, "height": 127}, {"class_id": 1, "top": 904, "left": 792, "width": 116, "height": 116}, {"class_id": 0, "top": 969, "left": 979, "width": 108, "height": 108}, {"class_id": 0, "top": 1064, "left": 1159, "width": 128, "height": 128}, {"class_id": 1, "top": 1077, "left": 1015, "width": 128, "height": 128}, {"class_id": 0, "top": 1218, "left": 1030, "width": 114, "height": 114}, {"class_id": 0, "top": 1108, "left": 944, "width": 95, "height": 95}, {"class_id": 0, "top": 988, "left": 821, "width": 114, "height": 114}], "categories": [{"class_id": 0, "name": "3clover"}, {"class_id": 1, "name": "4clover"}]}