{"file": "rotated_Screenshot (349)_270.jpg", "image_size": [{"width": 1200, "height": 1920, "depth": 3}], "annotations": [{"class_id": 1, "top": 897, "left": 603, "width": 114, "height": 167}, {"class_id": 1, "top": 1142, "left": 540, "width": 187, "height": 195}, {"class_id": 1, "top": 1301, "left": 332, "width": 114, "height": 112}, {"class_id": 1, "top": 928, "left": 873, "width": 66, "height": 54}, {"class_id": 1, "top": 617, "left": 522, "width": 66, "height": 66}, {"class_id": 1, "top": 494, "left": 376, "width": 63, "height": 66}, {"class_id": 1, "top": 603, "left": 370, "width": 57, "height": 60}, {"class_id": 1, "top": 698, "left": 378, "width": 57, "height": 63}, {"class_id": 1, "top": 700, "left": 273, "width": 53, "height": 53}, {"class_id": 1, "top": 496, "left": 263, "width": 63, "height": 61}, {"class_id": 1, "top": 506, "left": 187, "width": 54, "height": 49}, {"class_id": 1, "top": 603, "left": 169, "width": 49, "height": 56}, {"class_id": 1, "top": 698, "left": 183, "width": 59, "height": 58}, {"class_id": 1, "top": 534, "left": 537, "width": 44, "height": 48}], "categories": [{"class_id": 1, "name": "4clover"}]}