{"file": "rotated_Screenshot (117)_45.jpg", "image_size": [{"width": 2206, "height": 2206, "depth": 3}], "annotations": [{"class_id": 1, "top": 1022, "left": 553, "width": 195, "height": 195}, {"class_id": 1, "top": 1533, "left": 1017, "width": 99, "height": 99}, {"class_id": 1, "top": 1464, "left": 1022, "width": 137, "height": 137}, {"class_id": 1, "top": 913, "left": 1438, "width": 235, "height": 235}, {"class_id": 0, "top": 1086, "left": 712, "width": 115, "height": 115}, {"class_id": 0, "top": 1538, "left": 1119, "width": 145, "height": 145}, {"class_id": 0, "top": 1209, "left": 580, "width": 79, "height": 79}], "categories": [{"class_id": 0, "name": "3clover"}, {"class_id": 1, "name": "4clover"}]}