{"file": "rotated_Screenshot (143)_255.jpg", "image_size": [{"width": 1656, "height": 2165, "depth": 3}], "annotations": [{"class_id": 1, "top": 905, "left": 380, "width": 180, "height": 200}, {"class_id": 1, "top": 1041, "left": 647, "width": 129, "height": 133}, {"class_id": 1, "top": 983, "left": 726, "width": 94, "height": 109}, {"class_id": 1, "top": 1190, "left": 1056, "width": 115, "height": 117}, {"class_id": 1, "top": 1276, "left": 657, "width": 90, "height": 95}, {"class_id": 1, "top": 1335, "left": 652, "width": 124, "height": 113}, {"class_id": 1, "top": 1442, "left": 991, "width": 81, "height": 81}, {"class_id": 1, "top": 618, "left": 495, "width": 93, "height": 96}, {"class_id": 0, "top": 555, "left": 497, "width": 86, "height": 72}, {"class_id": 0, "top": 640, "left": 591, "width": 72, "height": 79}, {"class_id": 0, "top": 1508, "left": 927, "width": 53, "height": 48}, {"class_id": 0, "top": 1428, "left": 879, "width": 72, "height": 73}, {"class_id": 0, "top": 1326, "left": 965, "width": 88, "height": 92}, {"class_id": 0, "top": 1538, "left": 998, "width": 48, "height": 53}], "categories": [{"class_id": 0, "name": "3clover"}, {"class_id": 1, "name": "4clover"}]}