{"file": "rotated_Screenshot (111)_300.jpg", "image_size": [{"width": 1999, "height": 2262, "depth": 3}], "annotations": [{"class_id": 1, "top": 886, "left": 597, "width": 125, "height": 132}, {"class_id": 1, "top": 1256, "left": 751, "width": 48, "height": 50}, {"class_id": 0, "top": 1358, "left": 1107, "width": 122, "height": 123}, {"class_id": 1, "top": 1277, "left": 1151, "width": 113, "height": 111}, {"class_id": 0, "top": 1172, "left": 997, "width": 108, "height": 101}, {"class_id": 0, "top": 1016, "left": 827, "width": 121, "height": 126}, {"class_id": 1, "top": 1039, "left": 970, "width": 124, "height": 123}, {"class_id": 0, "top": 913, "left": 1006, "width": 113, "height": 106}, {"class_id": 0, "top": 1062, "left": 1075, "width": 94, "height": 91}, {"class_id": 0, "top": 1187, "left": 1150, "width": 116, "height": 104}], "categories": [{"class_id": 0, "name": "3clover"}, {"class_id": 1, "name": "4clover"}]}