{"file": "rotated_Screenshot (81)_165.jpg", "image_size": [{"width": 2165, "height": 1656, "depth": 3}], "annotations": [{"class_id": 1, "top": 854, "left": 1377, "width": 78, "height": 72}, {"class_id": 1, "top": 595, "left": 1403, "width": 82, "height": 95}, {"class_id": 0, "top": 775, "left": 1450, "width": 101, "height": 90}, {"class_id": 1, "top": 555, "left": 1497, "width": 84, "height": 84}, {"class_id": 1, "top": 473, "left": 1478, "width": 138, "height": 129}, {"class_id": 1, "top": 411, "left": 1076, "width": 85, "height": 89}, {"class_id": 1, "top": 930, "left": 734, "width": 60, "height": 59}], "categories": [{"class_id": 0, "name": "3clover"}, {"class_id": 1, "name": "4clover"}]}