{"file": "rotated_3fe8d84c7fbc43e1b01b85145a7c788e_285.jpg", "image_size": [{"width": 1656, "height": 2165, "depth": 3}], "annotations": [{"class_id": 1, "top": 838, "left": 305, "width": 96, "height": 96}, {"class_id": 0, "top": 794, "left": 315, "width": 65, "height": 61}, {"class_id": 0, "top": 766, "left": 221, "width": 92, "height": 91}, {"class_id": 0, "top": 871, "left": 208, "width": 78, "height": 82}], "categories": [{"class_id": 0, "name": "3clover"}, {"class_id": 1, "name": "4clover"}]}