{"file": "rotated_Screenshot (255)_90.jpg", "image_size": [{"width": 1200, "height": 1920, "depth": 3}], "annotations": [{"class_id": 1, "top": 612, "left": 486, "width": 117, "height": 112}, {"class_id": 1, "top": 658, "left": 893, "width": 84, "height": 80}, {"class_id": 1, "top": 906, "left": 862, "width": 127, "height": 102}, {"class_id": 1, "top": 1239, "left": 856, "width": 93, "height": 129}, {"class_id": 1, "top": 1250, "left": 224, "width": 78, "height": 88}, {"class_id": 0, "top": 682, "left": 214, "width": 59, "height": 68}], "categories": [{"class_id": 0, "name": "3clover"}, {"class_id": 1, "name": "4clover"}]}