{"file": "rotated_Screenshot (331)_150.jpg", "image_size": [{"width": 2262, "height": 1999, "depth": 3}], "annotations": [{"class_id": 1, "top": 702, "left": 775, "width": 196, "height": 205}, {"class_id": 1, "top": 1013, "left": 660, "width": 130, "height": 131}, {"class_id": 0, "top": 1087, "left": 708, "width": 109, "height": 107}, {"class_id": 0, "top": 1007, "left": 755, "width": 119, "height": 118}, {"class_id": 0, "top": 1142, "left": 663, "width": 90, "height": 85}, {"class_id": 0, "top": 1091, "left": 572, "width": 122, "height": 112}, {"class_id": 0, "top": 1050, "left": 615, "width": 109, "height": 103}, {"class_id": 0, "top": 924, "left": 593, "width": 141, "height": 142}, {"class_id": 0, "top": 764, "left": 681, "width": 149, "height": 149}, {"class_id": 0, "top": 880, "left": 830, "width": 101, "height": 96}], "categories": [{"class_id": 0, "name": "3clover"}, {"class_id": 1, "name": "4clover"}]}