{"file": "rotated_7ca01eef9b0c4cfd8284280a8194dbb7_210.jpg", "image_size": [{"width": 2262, "height": 1999, "depth": 3}], "annotations": [{"class_id": 1, "top": 464, "left": 1174, "width": 192, "height": 191}, {"class_id": 1, "top": 622, "left": 1205, "width": 172, "height": 168}, {"class_id": 1, "top": 914, "left": 665, "width": 62, "height": 58}, {"class_id": 1, "top": 737, "left": 549, "width": 54, "height": 54}, {"class_id": 0, "top": 850, "left": 718, "width": 50, "height": 48}, {"class_id": 0, "top": 900, "left": 570, "width": 49, "height": 48}, {"class_id": 0, "top": 881, "left": 820, "width": 47, "height": 43}, {"class_id": 0, "top": 800, "left": 707, "width": 50, "height": 47}, {"class_id": 0, "top": 759, "left": 725, "width": 55, "height": 54}, {"class_id": 0, "top": 900, "left": 729, "width": 47, "height": 44}, {"class_id": 0, "top": 862, "left": 543, "width": 60, "height": 57}, {"class_id": 0, "top": 683, "left": 645, "width": 63, "height": 62}, {"class_id": 0, "top": 663, "left": 698, "width": 53, "height": 50}], "categories": [{"class_id": 0, "name": "3clover"}, {"class_id": 1, "name": "4clover"}]}