{"file": "rotated_Screenshot (172)_30.jpg", "image_size": [{"width": 2262, "height": 1999, "depth": 3}], "annotations": [{"class_id": 1, "top": 909, "left": 665, "width": 102, "height": 102}, {"class_id": 1, "top": 1224, "left": 1215, "width": 250, "height": 247}, {"class_id": 1, "top": 605, "left": 1231, "width": 121, "height": 118}, {"class_id": 1, "top": 610, "left": 811, "width": 397, "height": 397}, {"class_id": 0, "top": 982, "left": 729, "width": 104, "height": 94}, {"class_id": 0, "top": 990, "left": 604, "width": 97, "height": 94}, {"class_id": 0, "top": 587, "left": 1290, "width": 82, "height": 83}, {"class_id": 0, "top": 697, "left": 1219, "width": 98, "height": 95}, {"class_id": 1, "top": 833, "left": 632, "width": 80, "height": 79}, {"class_id": 0, "top": 555, "left": 1269, "width": 68, "height": 66}, {"class_id": 0, "top": 526, "left": 1150, "width": 83, "height": 83}, {"class_id": 0, "top": 629, "left": 1189, "width": 56, "height": 56}], "categories": [{"class_id": 0, "name": "3clover"}, {"class_id": 1, "name": "4clover"}]}