{"file": "rotated_Screenshot (333)_285.jpg", "image_size": [{"width": 1656, "height": 2165, "depth": 3}], "annotations": [{"class_id": 1, "top": 685, "left": 964, "width": 128, "height": 147}, {"class_id": 1, "top": 1150, "left": 1060, "width": 316, "height": 297}, {"class_id": 1, "top": 788, "left": 332, "width": 109, "height": 114}, {"class_id": 0, "top": 814, "left": 390, "width": 149, "height": 135}, {"class_id": 0, "top": 684, "left": 401, "width": 118, "height": 131}, {"class_id": 1, "top": 1108, "left": 486, "width": 62, "height": 76}], "categories": [{"class_id": 0, "name": "3clover"}, {"class_id": 1, "name": "4clover"}]}