{"file": "rotated_437a15882c9d4883ac9887ecfdc8ac6b_330.jpg", "image_size": [{"width": 2262, "height": 1999, "depth": 3}], "annotations": [{"class_id": 1, "top": 610, "left": 1128, "width": 243, "height": 249}, {"class_id": 1, "top": 811, "left": 1452, "width": 166, "height": 170}, {"class_id": 1, "top": 770, "left": 681, "width": 221, "height": 229}, {"class_id": 1, "top": 895, "left": 992, "width": 206, "height": 199}, {"class_id": 1, "top": 1063, "left": 1204, "width": 275, "height": 263}, {"class_id": 1, "top": 1049, "left": 570, "width": 178, "height": 174}], "categories": [{"class_id": 1, "name": "4clover"}]}