{"file": "rotated_0630a0755511401bae6f07a72c36c6ee_60.jpg", "image_size": [{"width": 1999, "height": 2262, "depth": 3}], "annotations": [{"class_id": 1, "top": 1027, "left": 881, "width": 185, "height": 182}, {"class_id": 1, "top": 837, "left": 542, "width": 241, "height": 240}, {"class_id": 1, "top": 604, "left": 739, "width": 112, "height": 119}, {"class_id": 0, "top": 942, "left": 803, "width": 180, "height": 182}, {"class_id": 0, "top": 914, "left": 889, "width": 235, "height": 200}, {"class_id": 0, "top": 629, "left": 868, "width": 82, "height": 79}, {"class_id": 0, "top": 700, "left": 830, "width": 73, "height": 73}, {"class_id": 0, "top": 693, "left": 737, "width": 81, "height": 81}, {"class_id": 0, "top": 1106, "left": 812, "width": 141, "height": 136}], "categories": [{"class_id": 0, "name": "3clover"}, {"class_id": 1, "name": "4clover"}]}