{"file": "rotated_Screenshot (331)_255.jpg", "image_size": [{"width": 1656, "height": 2165, "depth": 3}], "annotations": [{"class_id": 1, "top": 1286, "left": 615, "width": 188, "height": 171}, {"class_id": 1, "top": 1395, "left": 950, "width": 117, "height": 117}, {"class_id": 0, "top": 1354, "left": 1010, "width": 95, "height": 99}, {"class_id": 0, "top": 1318, "left": 921, "width": 106, "height": 107}, {"class_id": 0, "top": 1410, "left": 1077, "width": 73, "height": 83}, {"class_id": 0, "top": 1481, "left": 1049, "width": 95, "height": 114}, {"class_id": 0, "top": 1460, "left": 999, "width": 89, "height": 101}, {"class_id": 0, "top": 1471, "left": 881, "width": 127, "height": 126}, {"class_id": 0, "top": 1420, "left": 703, "width": 134, "height": 133}, {"class_id": 0, "top": 1303, "left": 780, "width": 84, "height": 92}], "categories": [{"class_id": 0, "name": "3clover"}, {"class_id": 1, "name": "4clover"}]}