{"file": "rotated_b3fb4aa26dd145608a0b3ea4c8212239_150.jpg", "image_size": [{"width": 2262, "height": 1999, "depth": 3}], "annotations": [{"class_id": 1, "top": 1045, "left": 1283, "width": 255, "height": 254}, {"class_id": 1, "top": 650, "left": 1242, "width": 166, "height": 166}, {"class_id": 0, "top": 658, "left": 1166, "width": 79, "height": 73}, {"class_id": 0, "top": 1025, "left": 1411, "width": 170, "height": 179}], "categories": [{"class_id": 0, "name": "3clover"}, {"class_id": 1, "name": "4clover"}]}