{"file": "rotated_Screenshot (183)_270.jpg", "image_size": [{"width": 1200, "height": 1920, "depth": 3}], "annotations": [{"class_id": 1, "top": 591, "left": 873, "width": 78, "height": 83}, {"class_id": 1, "top": 904, "left": 874, "width": 99, "height": 105}, {"class_id": 1, "top": 608, "left": 210, "width": 69, "height": 103}, {"class_id": 1, "top": 1229, "left": 543, "width": 78, "height": 102}, {"class_id": 1, "top": 906, "left": 220, "width": 95, "height": 91}, {"class_id": 0, "top": 662, "left": 790, "width": 92, "height": 97}, {"class_id": 0, "top": 992, "left": 578, "width": 55, "height": 61}, {"class_id": 0, "top": 1330, "left": 545, "width": 92, "height": 82}, {"class_id": 0, "top": 697, "left": 217, "width": 88, "height": 82}, {"class_id": 0, "top": 893, "left": 785, "width": 96, "height": 81}], "categories": [{"class_id": 0, "name": "3clover"}, {"class_id": 1, "name": "4clover"}]}