{"file": "rotated_Screenshot (230)_75.jpg", "image_size": [{"width": 1656, "height": 2165, "depth": 3}], "annotations": [{"class_id": 1, "top": 1211, "left": 317, "width": 238, "height": 288}, {"class_id": 1, "top": 1029, "left": 753, "width": 144, "height": 140}, {"class_id": 1, "top": 1122, "left": 1074, "width": 95, "height": 86}, {"class_id": 1, "top": 835, "left": 1194, "width": 79, "height": 76}, {"class_id": 0, "top": 905, "left": 1261, "width": 78, "height": 92}, {"class_id": 0, "top": 1183, "left": 1191, "width": 65, "height": 76}, {"class_id": 0, "top": 1143, "left": 1191, "width": 69, "height": 77}], "categories": [{"class_id": 0, "name": "3clover"}, {"class_id": 1, "name": "4clover"}]}