{"file": "rotated_Screenshot (111)_0.jpg", "image_size": [{"width": 1920, "height": 1200, "depth": 3}], "annotations": [{"class_id": 1, "top": 748, "left": 591, "width": 104, "height": 84}, {"class_id": 1, "top": 848, "left": 962, "width": 39, "height": 33}, {"class_id": 0, "top": 551, "left": 1251, "width": 91, "height": 88}, {"class_id": 1, "top": 481, "left": 1197, "width": 80, "height": 84}, {"class_id": 0, "top": 574, "left": 1022, "width": 66, "height": 87}, {"class_id": 0, "top": 619, "left": 816, "width": 97, "height": 84}, {"class_id": 1, "top": 511, "left": 904, "width": 90, "height": 91}, {"class_id": 0, "top": 431, "left": 805, "width": 71, "height": 90}, {"class_id": 0, "top": 452, "left": 966, "width": 63, "height": 72}, {"class_id": 0, "top": 450, "left": 1112, "width": 64, "height": 97}], "categories": [{"class_id": 0, "name": "3clover"}, {"class_id": 1, "name": "4clover"}]}