{"file": "rotated_Screenshot (269)_90.jpg", "image_size": [{"width": 1200, "height": 1920, "depth": 3}], "annotations": [{"class_id": 1, "top": 917, "left": 441, "width": 154, "height": 184}, {"class_id": 1, "top": 580, "left": 534, "width": 87, "height": 101}, {"class_id": 1, "top": 642, "left": 436, "width": 61, "height": 84}, {"class_id": 1, "top": 864, "left": 773, "width": 132, "height": 123}, {"class_id": 1, "top": 545, "left": 778, "width": 178, "height": 206}, {"class_id": 1, "top": 1210, "left": 726, "width": 178, "height": 178}], "categories": [{"class_id": 1, "name": "4clover"}]}