{"file": "rotated_Screenshot (134)_60.jpg", "image_size": [{"width": 1999, "height": 2262, "depth": 3}], "annotations": [{"class_id": 1, "top": 1212, "left": 444, "width": 112, "height": 117}, {"class_id": 1, "top": 1342, "left": 751, "width": 144, "height": 141}, {"class_id": 1, "top": 814, "left": 1225, "width": 366, "height": 362}, {"class_id": 0, "top": 1138, "left": 556, "width": 97, "height": 97}, {"class_id": 0, "top": 1139, "left": 463, "width": 92, "height": 95}, {"class_id": 0, "top": 1287, "left": 424, "width": 111, "height": 99}, {"class_id": 0, "top": 1370, "left": 527, "width": 70, "height": 69}], "categories": [{"class_id": 0, "name": "3clover"}, {"class_id": 1, "name": "4clover"}]}