{"file": "rotated_Screenshot (64)_345.jpg", "image_size": [{"width": 2165, "height": 1656, "depth": 3}], "annotations": [{"class_id": 1, "top": 965, "left": 848, "width": 288, "height": 298}, {"class_id": 1, "top": 608, "left": 910, "width": 353, "height": 347}, {"class_id": 1, "top": 795, "left": 1360, "width": 123, "height": 103}, {"class_id": 1, "top": 1066, "left": 590, "width": 50, "height": 47}, {"class_id": 1, "top": 870, "left": 671, "width": 97, "height": 96}, {"class_id": 0, "top": 908, "left": 759, "width": 71, "height": 65}, {"class_id": 1, "top": 981, "left": 728, "width": 70, "height": 70}, {"class_id": 0, "top": 1125, "left": 695, "width": 67, "height": 70}, {"class_id": 1, "top": 943, "left": 612, "width": 48, "height": 50}, {"class_id": 0, "top": 1000, "left": 683, "width": 51, "height": 57}, {"class_id": 1, "top": 1038, "left": 718, "width": 66, "height": 61}, {"class_id": 1, "top": 1123, "left": 735, "width": 70, "height": 75}], "categories": [{"class_id": 0, "name": "3clover"}, {"class_id": 1, "name": "4clover"}]}