{"file": "rotated_Screenshot (16)_195.jpg", "image_size": [{"width": 2165, "height": 1656, "depth": 3}], "annotations": [{"class_id": 1, "top": 832, "left": 1060, "width": 83, "height": 84}, {"class_id": 1, "top": 820, "left": 660, "width": 247, "height": 273}, {"class_id": 1, "top": 592, "left": 616, "width": 182, "height": 170}, {"class_id": 1, "top": 629, "left": 726, "width": 137, "height": 133}, {"class_id": 0, "top": 797, "left": 944, "width": 92, "height": 87}, {"class_id": 0, "top": 773, "left": 989, "width": 63, "height": 65}, {"class_id": 1, "top": 1136, "left": 828, "width": 115, "height": 116}], "categories": [{"class_id": 0, "name": "3clover"}, {"class_id": 1, "name": "4clover"}]}