{"file": "rotated_fc0327c188b749ca89564f1b0f6224a7_75.jpg", "image_size": [{"width": 1656, "height": 2165, "depth": 3}], "annotations": [{"class_id": 1, "top": 1260, "left": 713, "width": 315, "height": 292}, {"class_id": 1, "top": 717, "left": 970, "width": 213, "height": 194}, {"class_id": 1, "top": 1143, "left": 1177, "width": 182, "height": 186}, {"class_id": 1, "top": 1444, "left": 1051, "width": 180, "height": 189}, {"class_id": 0, "top": 1342, "left": 1143, "width": 185, "height": 150}, {"class_id": 0, "top": 798, "left": 908, "width": 143, "height": 143}], "categories": [{"class_id": 0, "name": "3clover"}, {"class_id": 1, "name": "4clover"}]}