{"file": "rotated_Screenshot (335)_135.jpg", "image_size": [{"width": 2206, "height": 2206, "depth": 3}], "annotations": [{"class_id": 1, "top": 1516, "left": 1158, "width": 139, "height": 139}, {"class_id": 1, "top": 1445, "left": 1066, "width": 152, "height": 152}, {"class_id": 1, "top": 1400, "left": 982, "width": 147, "height": 147}, {"class_id": 1, "top": 738, "left": 1294, "width": 181, "height": 181}, {"class_id": 1, "top": 443, "left": 1016, "width": 207, "height": 207}, {"class_id": 1, "top": 955, "left": 1109, "width": 98, "height": 98}, {"class_id": 1, "top": 565, "left": 1040, "width": 219, "height": 219}], "categories": [{"class_id": 1, "name": "4clover"}]}