{"file": "rotated_Screenshot (173)_240.jpg", "image_size": [{"width": 1999, "height": 2262, "depth": 3}], "annotations": [{"class_id": 1, "top": 1270, "left": 650, "width": 230, "height": 228}, {"class_id": 1, "top": 765, "left": 1116, "width": 127, "height": 123}, {"class_id": 0, "top": 861, "left": 1393, "width": 107, "height": 110}, {"class_id": 0, "top": 940, "left": 1415, "width": 106, "height": 111}, {"class_id": 0, "top": 820, "left": 1305, "width": 90, "height": 92}, {"class_id": 0, "top": 800, "left": 1356, "width": 103, "height": 96}, {"class_id": 0, "top": 751, "left": 1053, "width": 95, "height": 94}, {"class_id": 0, "top": 785, "left": 919, "width": 145, "height": 140}, {"class_id": 0, "top": 642, "left": 1036, "width": 131, "height": 133}, {"class_id": 1, "top": 1461, "left": 988, "width": 96, "height": 97}, {"class_id": 1, "top": 925, "left": 1326, "width": 111, "height": 105}, {"class_id": 0, "top": 899, "left": 1239, "width": 83, "height": 80}, {"class_id": 0, "top": 871, "left": 1067, "width": 91, "height": 94}, {"class_id": 0, "top": 1041, "left": 1339, "width": 107, "height": 101}], "categories": [{"class_id": 0, "name": "3clover"}, {"class_id": 1, "name": "4clover"}]}