{"file": "rotated_Screenshot (42)_345.jpg", "image_size": [{"width": 2165, "height": 1656, "depth": 3}], "annotations": [{"class_id": 1, "top": 337, "left": 809, "width": 120, "height": 115}, {"class_id": 1, "top": 659, "left": 661, "width": 139, "height": 132}, {"class_id": 1, "top": 358, "left": 1070, "width": 181, "height": 156}, {"class_id": 1, "top": 1079, "left": 871, "width": 124, "height": 119}, {"class_id": 1, "top": 1092, "left": 982, "width": 109, "height": 103}, {"class_id": 1, "top": 1246, "left": 1207, "width": 69, "height": 71}, {"class_id": 0, "top": 1047, "left": 1244, "width": 59, "height": 51}, {"class_id": 0, "top": 1134, "left": 1246, "width": 73, "height": 65}, {"class_id": 0, "top": 1166, "left": 1155, "width": 68, "height": 63}, {"class_id": 0, "top": 1232, "left": 1286, "width": 58, "height": 58}, {"class_id": 0, "top": 1186, "left": 1332, "width": 51, "height": 53}, {"class_id": 0, "top": 1186, "left": 1372, "width": 71, "height": 75}, {"class_id": 0, "top": 1235, "left": 1338, "width": 94, "height": 90}, {"class_id": 0, "top": 1274, "left": 1263, "width": 95, "height": 86}, {"class_id": 0, "top": 1120, "left": 1173, "width": 56, "height": 50}], "categories": [{"class_id": 0, "name": "3clover"}, {"class_id": 1, "name": "4clover"}]}