{"file": "rotated_Screenshot (233)_60.jpg", "image_size": [{"width": 1999, "height": 2262, "depth": 3}], "annotations": [{"class_id": 1, "top": 1407, "left": 858, "width": 116, "height": 119}, {"class_id": 1, "top": 1089, "left": 993, "width": 171, "height": 172}, {"class_id": 1, "top": 737, "left": 892, "width": 142, "height": 147}, {"class_id": 1, "top": 618, "left": 895, "width": 132, "height": 133}, {"class_id": 1, "top": 877, "left": 654, "width": 283, "height": 286}, {"class_id": 0, "top": 669, "left": 976, "width": 132, "height": 129}], "categories": [{"class_id": 0, "name": "3clover"}, {"class_id": 1, "name": "4clover"}]}