{"file": "rotated_Screenshot (95)_75.jpg", "image_size": [{"width": 1656, "height": 2165, "depth": 3}], "annotations": [{"class_id": 1, "top": 1058, "left": 965, "width": 233, "height": 247}, {"class_id": 1, "top": 690, "left": 792, "width": 216, "height": 206}, {"class_id": 1, "top": 597, "left": 454, "width": 150, "height": 153}, {"class_id": 1, "top": 1415, "left": 936, "width": 124, "height": 121}, {"class_id": 0, "top": 936, "left": 492, "width": 140, "height": 149}, {"class_id": 1, "top": 886, "left": 347, "width": 180, "height": 202}, {"class_id": 0, "top": 623, "left": 596, "width": 91, "height": 110}], "categories": [{"class_id": 0, "name": "3clover"}, {"class_id": 1, "name": "4clover"}]}