{"file": "rotated_618ef9efb89b46f4b0632160f8be8cb1_345.jpg", "image_size": [{"width": 2165, "height": 1656, "depth": 3}], "annotations": [{"class_id": 1, "top": 352, "left": 776, "width": 161, "height": 161}, {"class_id": 1, "top": 381, "left": 1016, "width": 234, "height": 267}, {"class_id": 1, "top": 564, "left": 1390, "width": 149, "height": 153}, {"class_id": 1, "top": 801, "left": 1281, "width": 209, "height": 193}, {"class_id": 1, "top": 749, "left": 987, "width": 196, "height": 198}, {"class_id": 1, "top": 1062, "left": 900, "width": 173, "height": 167}, {"class_id": 0, "top": 383, "left": 686, "width": 83, "height": 85}, {"class_id": 0, "top": 289, "left": 778, "width": 74, "height": 76}, {"class_id": 0, "top": 286, "left": 830, "width": 60, "height": 51}, {"class_id": 0, "top": 315, "left": 862, "width": 79, "height": 80}, {"class_id": 0, "top": 474, "left": 868, "width": 73, "height": 71}, {"class_id": 0, "top": 485, "left": 676, "width": 62, "height": 60}, {"class_id": 0, "top": 563, "left": 904, "width": 51, "height": 51}, {"class_id": 0, "top": 552, "left": 840, "width": 51, "height": 46}, {"class_id": 0, "top": 612, "left": 677, "width": 84, "height": 96}, {"class_id": 1, "top": 710, "left": 676, "width": 125, "height": 122}, {"class_id": 0, "top": 814, "left": 761, "width": 79, "height": 70}, {"class_id": 0, "top": 752, "left": 846, "width": 57, "height": 50}, {"class_id": 0, "top": 694, "left": 845, "width": 51, "height": 48}, {"class_id": 0, "top": 557, "left": 1017, "width": 80, "height": 81}, {"class_id": 0, "top": 848, "left": 905, "width": 108, "height": 96}, {"class_id": 0, "top": 487, "left": 1335, "width": 91, "height": 89}, {"class_id": 0, "top": 589, "left": 1097, "width": 104, "height": 100}, {"class_id": 0, "top": 441, "left": 1444, "width": 83, "height": 63}, {"class_id": 0, "top": 687, "left": 1483, "width": 104, "height": 106}], "categories": [{"class_id": 0, "name": "3clover"}, {"class_id": 1, "name": "4clover"}]}