{"file": "rotated_67acad1c26f141fabfcb99c77ecd0cd9_300.jpg", "image_size": [{"width": 1999, "height": 2262, "depth": 3}], "annotations": [{"class_id": 1, "top": 899, "left": 1254, "width": 112, "height": 108}, {"class_id": 0, "top": 874, "left": 1249, "width": 76, "height": 76}, {"class_id": 0, "top": 835, "left": 1130, "width": 118, "height": 118}, {"class_id": 0, "top": 935, "left": 1148, "width": 128, "height": 128}], "categories": [{"class_id": 0, "name": "3clover"}, {"class_id": 1, "name": "4clover"}]}