{"file": "rotated_Screenshot (178)_315.jpg", "image_size": [{"width": 2206, "height": 2206, "depth": 3}], "annotations": [{"class_id": 1, "top": 1018, "left": 1519, "width": 91, "height": 91}, {"class_id": 1, "top": 1072, "left": 1506, "width": 71, "height": 71}, {"class_id": 1, "top": 843, "left": 1316, "width": 52, "height": 52}, {"class_id": 1, "top": 874, "left": 1299, "width": 60, "height": 60}, {"class_id": 0, "top": 909, "left": 1530, "width": 66, "height": 66}, {"class_id": 0, "top": 1123, "left": 1628, "width": 66, "height": 66}, {"class_id": 0, "top": 1061, "left": 1643, "width": 49, "height": 49}, {"class_id": 0, "top": 929, "left": 1564, "width": 71, "height": 71}, {"class_id": 1, "top": 1070, "left": 1008, "width": 115, "height": 115}], "categories": [{"class_id": 0, "name": "3clover"}, {"class_id": 1, "name": "4clover"}]}