{"file": "rotated_Screenshot (290)_90.jpg", "image_size": [{"width": 1200, "height": 1920, "depth": 3}], "annotations": [{"class_id": 1, "top": 863, "left": 807, "width": 216, "height": 292}, {"class_id": 1, "top": 921, "left": 650, "width": 158, "height": 162}, {"class_id": 1, "top": 896, "left": 504, "width": 140, "height": 173}, {"class_id": 1, "top": 589, "left": 597, "width": 150, "height": 152}, {"class_id": 1, "top": 1000, "left": 328, "width": 111, "height": 93}, {"class_id": 1, "top": 1220, "left": 312, "width": 81, "height": 93}, {"class_id": 1, "top": 1321, "left": 614, "width": 102, "height": 106}, {"class_id": 1, "top": 1244, "left": 599, "width": 99, "height": 82}, {"class_id": 0, "top": 1348, "left": 275, "width": 76, "height": 73}, {"class_id": 1, "top": 1231, "left": 845, "width": 59, "height": 51}, {"class_id": 1, "top": 1161, "left": 888, "width": 66, "height": 57}, {"class_id": 1, "top": 1279, "left": 959, "width": 51, "height": 54}, {"class_id": 1, "top": 1151, "left": 936, "width": 57, "height": 68}, {"class_id": 1, "top": 1295, "left": 1060, "width": 63, "height": 57}, {"class_id": 1, "top": 1238, "left": 1050, "width": 53, "height": 62}, {"class_id": 1, "top": 1341, "left": 963, "width": 51, "height": 40}, {"class_id": 0, "top": 1346, "left": 443, "width": 41, "height": 46}, {"class_id": 0, "top": 1373, "left": 421, "width": 48, "height": 44}, {"class_id": 0, "top": 1273, "left": 198, "width": 87, "height": 80}, {"class_id": 0, "top": 954, "left": 331, "width": 72, "height": 60}, {"class_id": 0, "top": 921, "left": 195, "width": 75, "height": 76}, {"class_id": 0, "top": 841, "left": 410, "width": 63, "height": 88}], "categories": [{"class_id": 0, "name": "3clover"}, {"class_id": 1, "name": "4clover"}]}